FOntCell/OBO_Formating.py
FOntCell/Ontology_parse.py
FOntCell/Tree_com.py
FOntCell/__init__.py
FOntCell/circ_ontology.py
FOntCell/coord_taker.py
FOntCell/doc_managing.py
FOntCell/fontcell_main.py
FOntCell/fusion_parallelized.py
FOntCell/makeFigures.py
FOntCell/ontology_fusion.py
FOntCell/pyhtml.py
FOntCell/read_configuration.py
FOntCell/fontcell_demo/CELDA_import.owl
FOntCell/fontcell_demo/LifeMap_parsed.ods
FOntCell/fontcell_demo/demo_configurations.txt
FOntCell/fontcell_demo/file_clean_CELDA.txt
FOntCell/fontcell_demo/logo.png
fontcell-1.6.1.data/data/FOntCell/fontcell_demo/CELDA_import.owl
fontcell-1.6.1.data/data/FOntCell/fontcell_demo/LifeMap_parsed.ods
fontcell-1.6.1.data/data/FOntCell/fontcell_demo/demo_configurations.txt
fontcell-1.6.1.data/data/FOntCell/fontcell_demo/file_clean_CELDA.txt
fontcell-1.6.1.data/data/FOntCell/fontcell_demo/logo.png
fontcell-1.6.1.dist-info/LICENSE
fontcell-1.6.1.dist-info/METADATA
fontcell-1.6.1.dist-info/WHEEL
fontcell-1.6.1.dist-info/top_level.txt
fontcell-1.6.1.dist-info/RECORD
